TOPSIS_Mehak_101983050/__init__.py
TOPSIS_Mehak_101983050-1.0.1.dist-info/Licence.txt
TOPSIS_Mehak_101983050-1.0.1.dist-info/METADATA
TOPSIS_Mehak_101983050-1.0.1.dist-info/WHEEL
TOPSIS_Mehak_101983050-1.0.1.dist-info/top_level.txt
TOPSIS_Mehak_101983050-1.0.1.dist-info/RECORD
