Metadata-Version: 2.1
Name: TOPSIS-Mehak-101983050
Version: 1.0.1
Summary: Assignment06
Home-page: https://github.com/Mehak-Munjal/TOPSIS
Author: Mehak
Author-email: UNKNOWN
License: MIT
Keywords: Topsis,Vector,normalization,score
Platform: UNKNOWN
Classifier: Programming Language :: Python :: 3
Classifier: License :: OSI Approved :: MIT License
Classifier: Operating System :: OS Independent
Requires-Dist: pandas
